LICENSE.txt
README.md
pyproject.toml
setup.py
src/matlab/__init__.py
src/matlab/engine/__init__.py
src/matlab/engine/basefuture.py
src/matlab/engine/engineerror.py
src/matlab/engine/enginehelper.py
src/matlab/engine/enginesession.py
src/matlab/engine/fevalfuture.py
src/matlab/engine/futureresult.py
src/matlab/engine/matlabengine.py
src/matlab/engine/matlabfuture.py
src/matlabengine.egg-info/PKG-INFO
src/matlabengine.egg-info/SOURCES.txt
src/matlabengine.egg-info/dependency_links.txt
src/matlabengine.egg-info/not-zip-safe
src/matlabengine.egg-info/top_level.txt