Metadata-Version: 2.1
Name: matlabengine
Version: 26.1.1
Summary: A module to call MATLAB from Python
Home-page: https://github.com/mathworks/matlab-engine-for-python/
Author: MathWorks
License: LICENSE.txt, located in this repository
Project-URL: Documentation, https://www.mathworks.com/help/matlab/matlab-engine-for-python.html
Project-URL: Source, https://github.com/mathworks/matlab-engine-for-python
Project-URL: Tracker, https://github.com/mathworks/matlab-engine-for-python/issues
Keywords: MATLAB,MATLAB Engine for Python
Platform: UNKNOWN
Classifier: Natural Language :: English
Classifier: Intended Audience :: Developers
Classifier: Programming Language :: Python :: 3.9
Classifier: Programming Language :: Python :: 3.10
Classifier: Programming Language :: Python :: 3.11
Classifier: Programming Language :: Python :: 3.12
Classifier: Programming Language :: Python :: 3.13
Requires-Python: >=3.9, <3.14
License-File: LICENSE.txt
